silent_compute/__init__.py
silent_compute/sil_compute/__init__.py
silent_compute/sil_compute/cfm.py
silent_compute/sil_compute/core.py
silent_compute/sil_compute/psi.py
silent_compute-0.1.0.dist-info/LICENSE
silent_compute-0.1.0.dist-info/METADATA
silent_compute-0.1.0.dist-info/WHEEL
silent_compute-0.1.0.dist-info/top_level.txt
silent_compute-0.1.0.dist-info/RECORD
